spacecutter_lightning/__init__.py
spacecutter_lightning/callback.py
spacecutter_lightning-1.0.1.dist-info/METADATA
spacecutter_lightning-1.0.1.dist-info/WHEEL
spacecutter_lightning-1.0.1.dist-info/RECORD
