Metadata-Version: 2.1
Name: spacecutter-lightning
Version: 1.0.1
Summary: PyTorch-Lightning callback for spacecutter
Home-page: https://github.com/soof-golan/spacecutter-lightning
License: MIT
Author: Soof Golan
Author-email: pypi@soofgolan.com
Requires-Python: >=3.8,<4.0
Classifier: License :: OSI Approved :: MIT License
Classifier: Programming Language :: Python :: 3
Classifier: Programming Language :: Python :: 3.8
Classifier: Programming Language :: Python :: 3.9
Classifier: Programming Language :: Python :: 3.10
Classifier: Programming Language :: Python :: 3.11
Requires-Dist: pytorch-lightning (>=2.0.1,<3.0.0)
Requires-Dist: spacecutter-torch (>=1.0.0,<2.0.0)
Project-URL: Repository, https://github.com/soof-golan/spacecutter-lightning
